src/pipe_MIPS32.v
module pipe_MIPS32 (clk1,clk2);
    input clk1, clk2;
    reg [31:0] PC, IF_ID_IR, IF_ID_NPC;
    reg [31:0] ID_EX_IR, ID_EX_NPC, ID_EX_A, ID_EX_B, ID_EX_Imm;
    reg [2:0] ID_EX_type, EX_MEM_type, MEM_WB_type;
    reg [31:0] EX_MEM_IR, EX_MEM_ALUOut, EX_MEM_B;
    reg EX_MEM_cond;
    reg [31:0] MEM_WB_IR, MEM_WB_ALUOut, MEM_WB_LMD;
    reg [31:0] Reg [0:31];
    reg [31:0] Mem [0:1023];

    parameter ADD=6'b000000, SUB=6'b000001, AND=6'b000010, OR=6'b000011,
              SLT=6'b000100, MUL=6'b000101, HLT=6'b111111,
              LW=6'b001000, SW=6'b001001, ADDI=6'b001010, SUBI=6'b001011, SLTI=6'b001100,
              BNEQZ=6'b001101, BEQZ=6'b001110;

    parameter RR_ALU=3'b000, RM_ALU=3'b001, LOAD=3'b010, STORE=3'b011,
              BRANCH=3'b100, HALT=3'b101;
    reg HALTED;
    reg TAKEN_BRANCH;

    always @(posedge clk1) //IF STAGE
        if (HALTED==0)
        begin
            if(((EX_MEM_IR[31:26] == BEQZ) && (EX_MEM_cond == 1)) || ((EX_MEM_IR[31:26] == BNEQZ) && (EX_MEM_cond == 0)))
                begin
                    IF_ID_IR <= #2 Mem[EX_MEM_ALUOut];
                    TAKEN_BRANCH <= #2 1'b1;
                    IF_ID_NPC <= #2 EX_MEM_ALUOut + 1;
                    PC <= #2 EX_MEM_ALUOut +1;
                end 
            else
                begin
                    IF_ID_IR <= #2 Mem[PC];
                    IF_ID_NPC <= #2 PC +1;
                    PC <= #2 PC +1;
                end
        end  

    always @(posedge clk2) //ID STAGE
        if (HALTED == 0)
        begin
            if(IF_ID_IR[25:21]  == 5'b00000) ID_EX_A <= 0;
            else ID_EX_A <= #2 Reg[IF_ID_IR[25:21]]; //rs

            if(IF_ID_IR[20:16] == 5'b00000) ID_EX_B <= 0;
            else ID_EX_B <= #2 Reg[IF_ID_IR[20:16]]; //rt

            ID_EX_NPC <= #2 IF_ID_NPC;
            ID_EX_IR <= #2 IF_ID_IR;
            ID_EX_Imm <= #2 {{16{IF_ID_IR[15]}}, IF_ID_IR[15:0]}; //sign-extended immediate
            case (IF_ID_IR[31:26])
                ADD, SUB, AND, OR, SLT, MUL: ID_EX_type <= #2 RR_ALU;
                ADDI, SUBI, SLTI: ID_EX_type <= #2 RM_ALU;
                LW: ID_EX_type <= #2 LOAD;
                SW: ID_EX_type <= #2 STORE;
                BEQZ, BNEQZ: ID_EX_type <= #2 BRANCH;
                HLT: ID_EX_type <= #2 HALT;
                default: ID_EX_type <= #2 HALT; 
            endcase
        end

    always @(posedge clk1) //EX STAGE
        if (HALTED == 0)
        begin
            EX_MEM_type <= #2 ID_EX_type;
            EX_MEM_IR <= #2 ID_EX_IR;
            TAKEN_BRANCH <= #2 0;
            case (ID_EX_type)
                RR_ALU: begin
                            case(ID_EX_IR[31:26]) //"OPCODE"
                                ADD: EX_MEM_ALUOut <= #2 ID_EX_A + ID_EX_B;
                                SUB: EX_MEM_ALUOut <= #2 ID_EX_A - ID_EX_B;
                                AND: EX_MEM_ALUOut <= #2 ID_EX_A & ID_EX_B;
                                OR:  EX_MEM_ALUOut <= #2 ID_EX_A | ID_EX_B;
                                SLT: EX_MEM_ALUOut <= #2 ID_EX_A < ID_EX_B;
                                MUL: EX_MEM_ALUOut <= #2 ID_EX_A * ID_EX_B;
                                default: EX_MEM_ALUOut <= #2 32'hxxxxxxxx;
                            endcase
                        end
                RM_ALU: begin
                            case(ID_EX_IR[31:26]) //"OPCODE"
                                ADDI: EX_MEM_ALUOut <= #2 ID_EX_A + ID_EX_Imm;
                                SUBI: EX_MEM_ALUOut <= #2 ID_EX_A - ID_EX_Imm;
                                SLTI: EX_MEM_ALUOut <= #2 ID_EX_A < ID_EX_Imm;
                                default: EX_MEM_ALUOut <= #2 32'hxxxxxxxx;
                            endcase
                        end
                LOAD, STORE:
                        begin
                            EX_MEM_ALUOut <= #2 ID_EX_A + ID_EX_Imm; //effective address
                            EX_MEM_B <= #2 ID_EX_B; //for SW
                        end
                BRANCH:
                        begin
                            EX_MEM_ALUOut <= #2 ID_EX_NPC + ID_EX_Imm; //branch target address
                            EX_MEM_cond <= #2 (ID_EX_A == 0);//condition
                        end
            endcase
        end

    always @(posedge clk2) //MEM STAGE
        if (HALTED == 0)
        begin
            MEM_WB_type <= #2 EX_MEM_type;
            MEM_WB_IR <= #2 EX_MEM_IR;
            case (EX_MEM_type)
                RR_ALU, RM_ALU: 
                        MEM_WB_ALUOut <= #2 EX_MEM_ALUOut;
                LOAD:   MEM_WB_LMD <= #2 Mem[EX_MEM_ALUOut];
                STORE:  if (TAKEN_BRANCH == 0) //Disable write
                            Mem[EX_MEM_ALUOut] <= #2 EX_MEM_B;
            endcase
        end              

    always @(posedge clk1) //WB STAGE
        begin 
            if(TAKEN_BRANCH == 0)
            case (MEM_WB_type)
                RR_ALU: Reg[MEM_WB_IR[15:11]] <= #2 MEM_WB_ALUOut; //rd
                RM_ALU: Reg[MEM_WB_IR[20:16]] <= #2 MEM_WB_ALUOut; //rt
                LOAD:   Reg[MEM_WB_IR[20:16]] <= #2 MEM_WB_LMD; //rt
                HALT:   HALTED <= #2 1'b1;
            endcase
        end
endmodule

testbench/test_eg3.v
module test_eg3;
    reg clk1, clk2;
    integer k;
    pipe_MIPS32 mips(clk1, clk2);
    initial
        begin
            clk1=0; clk2=0;
            repeat(20)
                begin
                    #5 clk1=1; #5 clk1=0;
                    #5 clk2=1; #5 clk2=0;
                end
        end

    initial
        begin
            for(k=0; k<31; k++)
                mips.Reg[k] = k;
                

                mips.Mem[0]  = 32'h280a00c8; // ADDI R10,R0,200
                mips.Mem[1]  = 32'h28020001; // ADDI R2,R0,1
                mips.Mem[2]  = 32'h0e94a000; // OR R20,R20,R20 (dummy)
                mips.Mem[3]  = 32'h21430000; // LW R3,0(R10)
                mips.Mem[4]  = 32'h0e94a000; // OR R20,R20,R20 (dummy)
                mips.Mem[5]  = 32'h14431000; // MUL R2,R2,R3
                mips.Mem[6]  = 32'h2c630001; // SUBI R3,R3,1
                mips.Mem[7]  = 32'h0e94a000; // OR R20,R20,R20 (dummy)
                mips.Mem[8]  = 32'h3460fffc; // BNEQZ R3,Loop
                mips.Mem[9]  = 32'h2542fffe; // SW R2,-2(R10)
                mips.Mem[10] = 32'hfc000000; // HLT

                mips.Mem[200] = 4;

                mips.PC = 0;
                mips.HALTED = 0;
                mips.TAKEN_BRANCH = 0;

                #2000 $display("Mem[200]: %2d, Mem[198]: %6d", mips.Mem[200], mips.Mem[198]); 
        end

    initial
        begin
            $dumpfile("test_mips32_eg3.vcd");
            $dumpvars(0, test_eg3);
            $monitor("R2: %4d", mips.Reg[2]);
            #3000 $finish;
        end
endmodule

results/test_mips32_eg3.vcd
$date
	Fri Sep 19 23:11:54 2025
$end
$version
	Icarus Verilog
$end
$timescale
	1s
$end
$scope module test_eg3 $end
$var reg 1 ! clk1 $end
$var reg 1 " clk2 $end
$var integer 32 # k [31:0] $end
$scope module mips $end
$var wire 1 ! clk1 $end
$var wire 1 " clk2 $end
$var parameter 6 $ ADD $end
$var parameter 6 % ADDI $end
$var parameter 6 & AND $end
$var parameter 6 ' BEQZ $end
$var parameter 6 ( BNEQZ $end
$var parameter 3 ) BRANCH $end
$var parameter 3 * HALT $end
$var parameter 6 + HLT $end
$var parameter 3 , LOAD $end
$var parameter 6 - LW $end
$var parameter 6 . MUL $end
$var parameter 6 / OR $end
$var parameter 3 0 RM_ALU $end
$var parameter 3 1 RR_ALU $end
$var parameter 6 2 SLT $end
$var parameter 6 3 SLTI $end
$var parameter 3 4 STORE $end
$var parameter 6 5 SUB $end
$var parameter 6 6 SUBI $end
$var parameter 6 7 SW $end
$var reg 32 8 EX_MEM_ALUOut [31:0] $end
$var reg 32 9 EX_MEM_B [31:0] $end
$var reg 32 : EX_MEM_IR [31:0] $end
$var reg 1 ; EX_MEM_cond $end
$var reg 3 < EX_MEM_type [2:0] $end
$var reg 1 = HALTED $end
$var reg 32 > ID_EX_A [31:0] $end
$var reg 32 ? ID_EX_B [31:0] $end
$var reg 32 @ ID_EX_IR [31:0] $end
$var reg 32 A ID_EX_Imm [31:0] $end
$var reg 32 B ID_EX_NPC [31:0] $end
$var reg 3 C ID_EX_type [2:0] $end
$var reg 32 D IF_ID_IR [31:0] $end
$var reg 32 E IF_ID_NPC [31:0] $end
$var reg 32 F MEM_WB_ALUOut [31:0] $end
$var reg 32 G MEM_WB_IR [31:0] $end
$var reg 32 H MEM_WB_LMD [31:0] $end
$var reg 3 I MEM_WB_type [2:0] $end
$var reg 32 J PC [31:0] $end
$var reg 1 K TAKEN_BRANCH $end
$upscope $end
$upscope $end
$enddefinitions $end
$comment Show the parameter values. $end
$dumpall
b1001 7
b1011 6
b1 5
b11 4
b1100 3
b100 2
b0 1
b1 0
b11 /
b101 .
b1000 -
b10 ,
b111111 +
b101 *
b100 )
b1101 (
b1110 '
b10 &
b1010 %
b0 $
$end
#0
$dumpvars
0K
b0 J
bx I
bx H
bx G
bx F
bx E
bx D
bx C
bx B
bx A
bx @
bx ?
bx >
0=
bx <
x;
bx :
bx 9
bx 8
b11111 #
0"
0!
$end
#5
1!
#7
b1 J
b1 E
b101000000010100000000011001000 D
#10
0!
#15
b0 >
1"
#17
b1 C
b11001000 A
b101000000010100000000011001000 @
b1 B
b1010 ?
#20
0"
#25
1!
#27
b11001000 8
b101000000010100000000011001000 :
b1 <
b10 J
b10 E
b101000000000100000000000000001 D
#30
0!
#35
1"
#37
b11001000 F
b101000000010100000000011001000 G
b1 I
b1 A
b101000000000100000000000000001 @
b10 B
b10 ?
#40
0"
#45
1!
#47
b11 J
b11 E
b1110100101001010000000000000 D
b1 8
b101000000000100000000000000001 :
#50
0!
#55
1"
#57
b0 C
b11111111111111111010000000000000 A
b1110100101001010000000000000 @
b11 B
b10100 ?
b10100 >
b1 F
b101000000000100000000000000001 G
#60
0"
#65
1!
#67
b10100 8
b1110100101001010000000000000 :
b0 <
b100 J
b100 E
b100001010000110000000000000000 D
#70
0!
#75
1"
#77
b10100 F
b1110100101001010000000000000 G
b0 I
b10 C
b0 A
b100001010000110000000000000000 @
b100 B
b11 ?
b11001000 >
#80
0"
#85
1!
#87
b101 J
b101 E
b1110100101001010000000000000 D
b11 9
b11001000 8
b100001010000110000000000000000 :
b10 <
#90
0!
#95
1"
#97
b0 C
b11111111111111111010000000000000 A
b1110100101001010000000000000 @
b101 B
b10100 ?
b10100 >
b100 H
b100001010000110000000000000000 G
b10 I
#100
0"
#105
1!
#107
b10100 8
b1110100101001010000000000000 :
b0 <
b110 J
b110 E
b10100010000110001000000000000 D
#110
0!
#115
1"
#117
b1110100101001010000000000000 G
b0 I
b1000000000000 A
b10100010000110001000000000000 @
b110 B
b100 ?
b1 >
#120
0"
#125
1!
#127
b111 J
b111 E
b101100011000110000000000000001 D
b100 8
b10100010000110001000000000000 :
#130
0!
#135
1"
#137
b1 C
b1 A
b101100011000110000000000000001 @
b111 B
b100 >
b100 F
b10100010000110001000000000000 G
#140
0"
#145
1!
#147
b11 8
b101100011000110000000000000001 :
b1 <
b1000 J
b1000 E
b1110100101001010000000000000 D
#150
0!
#155
1"
#157
b11 F
b101100011000110000000000000001 G
b1 I
b0 C
b11111111111111111010000000000000 A
b1110100101001010000000000000 @
b1000 B
b10100 ?
b10100 >
#160
0"
#165
1!
#167
b1001 J
b1001 E
b110100011000001111111111111100 D
b10100 8
b1110100101001010000000000000 :
b0 <
#170
0!
#175
b0 ?
1"
#177
b100 C
b11111111111111111111111111111100 A
b110100011000001111111111111100 @
b1001 B
b11 >
b10100 F
b1110100101001010000000000000 G
b0 I
#180
0"
#185
1!
#187
0;
b101 8
b110100011000001111111111111100 :
b100 <
b1010 J
b1010 E
b100101010000101111111111111110 D
#190
0!
#195
1"
#197
b110100011000001111111111111100 G
b100 I
b11 C
b11111111111111111111111111111110 A
b100101010000101111111111111110 @
b1010 B
b100 ?
b11001000 >
#200
0"
#205
1!
#207
b110 J
b110 E
1K
b10100010000110001000000000000 D
b100 9
b11000110 8
b100101010000101111111111111110 :
b11 <
#210
0!
#215
1"
#217
b0 C
b1000000000000 A
b10100010000110001000000000000 @
b110 B
b11 ?
b100 >
b100101010000101111111111111110 G
b11 I
#220
0"
#225
1!
#227
b1100 8
0K
b10100010000110001000000000000 :
b0 <
b111 J
b111 E
b101100011000110000000000000001 D
#230
0!
#235
1"
#237
b1100 F
b10100010000110001000000000000 G
b0 I
b1 C
b1 A
b101100011000110000000000000001 @
b111 B
b11 >
#240
0"
#245
1!
#247
b1000 J
b1000 E
b1110100101001010000000000000 D
b10 8
b101100011000110000000000000001 :
b1 <
#250
0!
#255
1"
#257
b0 C
b11111111111111111010000000000000 A
b1110100101001010000000000000 @
b1000 B
b10100 ?
b10100 >
b10 F
b101100011000110000000000000001 G
b1 I
#260
0"
#265
1!
#267
b10100 8
b1110100101001010000000000000 :
b0 <
b1001 J
b1001 E
b110100011000001111111111111100 D
#270
0!
#275
b0 ?
1"
#277
b10100 F
b1110100101001010000000000000 G
b0 I
b100 C
b11111111111111111111111111111100 A
b110100011000001111111111111100 @
b1001 B
b10 >
#280
0"
#285
1!
#287
b1010 J
b1010 E
b100101010000101111111111111110 D
b101 8
b110100011000001111111111111100 :
b100 <
#290
0!
#295
1"
#297
b11 C
b11111111111111111111111111111110 A
b100101010000101111111111111110 @
b1010 B
b1100 ?
b11001000 >
b110100011000001111111111111100 G
b100 I
#300
0"
#305
1!
#307
b1100 9
b11000110 8
b100101010000101111111111111110 :
b11 <
b110 J
b110 E
0K
b10100010000110001000000000000 D
#310
0!
#315
1"
#317
b100101010000101111111111111110 G
b11 I
b0 C
b1000000000000 A
b10100010000110001000000000000 @
b110 B
b10 ?
b1100 >
#320
0"
#325
1!
#327
b111 J
b111 E
b101100011000110000000000000001 D
b11000 8
b10100010000110001000000000000 :
b0 <
#330
0!
#335
1"
#337
b1 C
b1 A
b101100011000110000000000000001 @
b111 B
b10 >
b11000 F
b10100010000110001000000000000 G
b0 I
#340
0"
#345
1!
#347
b1 8
b101100011000110000000000000001 :
b1 <
b1000 J
b1000 E
b1110100101001010000000000000 D
#350
0!
#355
1"
#357
b1 F
b101100011000110000000000000001 G
b1 I
b0 C
b11111111111111111010000000000000 A
b1110100101001010000000000000 @
b1000 B
b10100 ?
b10100 >
#360
0"
#365
1!
#367
b1001 J
b1001 E
b110100011000001111111111111100 D
b10100 8
b1110100101001010000000000000 :
b0 <
#370
0!
#375
b0 ?
1"
#377
b100 C
b11111111111111111111111111111100 A
b110100011000001111111111111100 @
b1001 B
b1 >
b10100 F
b1110100101001010000000000000 G
b0 I
#380
0"
#385
1!
#387
b101 8
b110100011000001111111111111100 :
b100 <
b1010 J
b1010 E
b100101010000101111111111111110 D
#390
0!
#395
1"
#397
b110100011000001111111111111100 G
b100 I
b11 C
b11111111111111111111111111111110 A
b100101010000101111111111111110 @
b1010 B
b11000 ?
b11001000 >
